<?xml version="1.0" encoding="UTF-8"?>
<diagrams>
  <diagram name="cache">
    <command command-class="de.frag.umlplugin.uml.command.AddClassCommand" psi-class="se.awesomoe.pm.cache.CacheState" />
    <command command-class="de.frag.umlplugin.uml.command.AddDependentClassesCommand" psi-class="se.awesomoe.pm.cache.CacheState" />
    <command command-class="de.frag.umlplugin.uml.command.AddDependentClassesCommand" psi-class="se.awesomoe.pm.cache.AbstractManagerWithCache" />
    <command command-class="de.frag.umlplugin.uml.command.AddDependentClassesCommand" psi-class="se.awesomoe.pm.cache.CacheFactory" />
    <compartment-visibility>
      <show-fields class="se.awesomoe.pm.cache.AbstractManagerWithCache" />
      <show-methods class="se.awesomoe.pm.cache.CacheSettings" />
      <show-methods class="se.awesomoe.pm.cache.CacheObject" />
      <show-methods class="se.awesomoe.pm.cache.CacheFactory" />
      <show-methods class="se.awesomoe.pm.cache.AbstractManagerWithCache" />
      <show-methods class="se.awesomoe.pm.cache.CacheState" />
      <show-methods class="se.awesomoe.pm.cache.CachedManager" />
    </compartment-visibility>
  </diagram>
</diagrams>

